{
  "recipes": [
    {
      "name": "Basic Hamburger",
      "canDeliver": true,
      "requiredIngredients": [
        {"name": "Bun", "requiredState": ["Cut"]},
        {"name": "Meat", "requiredState": ["Cut", "Fried"]}
        
      ]
    },
    {
      "name": "Cheeseburger",
      "canDeliver": true,
      "requiredIngredients": [
        {"name": "Bun", "requiredState": ["Cut"]},
        {"name": "Meat", "requiredState": ["Cut", "Fried"]},
        {"name": "Cheese", "requiredState": ["Cut", "Fried"]}
        
      ]
    },
    {
      "name": "Lettuce Hamburger",
      "canDeliver": true,
      "requiredIngredients": [
        {"name": "Bun", "requiredState": ["Cut"]},
        {"name": "Meat", "requiredState": ["Cut", "Fried"]},
        {"name": "Lettuce", "requiredState": ["Cut"]}
        
      ]
    },
    {
      "name": "Supreme Hamburger",
      "canDeliver": true,
      "requiredIngredients": [
        {"name": "Bun", "requiredState": ["Cut"]},
        {"name": "Meat", "requiredState": ["Cut", "Fried"]},
        {"name": "Lettuce", "requiredState": ["Cut"]},
        {"name": "Tomato", "requiredState": ["Cut"]},
        {"name": "Cheese", "requiredState": ["Cut", "Fried"]}
      ]
    },
    {
      "name": "pancake batter",
      "canDeliver": false,
      "requiredIngredients": [
        {"name": "flour", "requiredState": ["Mix"]},
        {"name": "Egg", "requiredState": ["Mix"]}
        
      ]
    },
    {
      "name": "blueberry pancake batter",
      "canDeliver": false,
      "requiredIngredients": [
        {"name": "flour", "requiredState": ["Mix"]},
        {"name": "Egg", "requiredState": ["Mix"]},
        {"name": "Blueberry", "requiredState": ["Cut"]}
        
      ]
    },
    {
      "name": "chocolate batter",
      "canDeliver": false,
      "requiredIngredients": [
        {"name": "flour", "requiredState": ["Mix"]},
        {"name": "Egg", "requiredState": ["Mix"]},
        {"name": "Chocolate", "requiredState": ["Cut"]}
        
      ]
    },
    {
      "name": "strawberry pancake batter",
      "canDeliver": false,
      "requiredIngredients": [
        {"name": "flour", "requiredState": ["Mix"]},
        {"name": "Egg", "requiredState": ["Mix"]},
        {"name": "Strawberry", "requiredState": ["Cut"]}
      ]
    },
    {
      "name": "pancake",
      "canDeliver": true,
      "requiredIngredients": [
        {"name": "pancake batter", "requiredState": ["Fried"]}
        
      ]
    },
    {
      "name": "blueberry pancake",
      "canDeliver": true,
      "requiredIngredients": [
        {"name": "blueberry pancake batter", "requiredState": ["Fried"]}
        

      ]
    },
    {
      "name": "chocolate pancake",
      "canDeliver": true,
      "requiredIngredients": [
        {"name": "chocolate batter", "requiredState": ["Fried"]}
      ]
    },
    {
      "name": "strawberry pancake",
      "canDeliver": true,
      "requiredIngredients": [
        {"name": "strawberry pancake batter", "requiredState": ["Fried"]}
      ]
    },
    {
      "name": "chocolate donut",
        "canDeliver": true,
      "requiredIngredients": [
        {"name": "chocolate batter", "requiredState": ["DeepFried"]}
      ]
    },
    {
      "name": "honey donut batter",
      "canDeliver": false,
      "requiredIngredients": [
        {"name": "flour", "requiredState": ["Mix"]},
        {"name": "Egg", "requiredState": ["Mix"]},
        {"name": "Honeycomb", "requiredState": ["Cut"]}
      ]
    },
    {
      "name": "raspberry donut batter",
      "canDeliver": false,
      "requiredIngredients": [
        {"name": "flour", "requiredState": ["Mix"]},
        {"name": "Egg", "requiredState": ["Mix"]},
        {"name": "Raspberry", "requiredState": ["Cut"]}
      ]
    },
    {
      "name": "honey donut",
      "canDeliver": true,
      "requiredIngredients": [
        {"name": "honey donut batter", "requiredState": ["DeepFried"]}
      ]
    },
    {
      "name": "raspberry donut",
      "canDeliver": true,
      "requiredIngredients": [
        {"name": "raspberry donut batter", "requiredState": ["DeepFried"]}
      ]
    },
    {
      "name": "sushi",
      "canDeliver": true,
      "requiredIngredients": [
        {"name": "Rice", "requiredState": ["Boiled"]},
        {"name": "Fish", "requiredState": ["Cut"]},
        {"name": "Nori", "requiredState": ["Cut"]}
      ]
    },
    {
      "name": "cucumber sushi",
      "canDeliver": true,
      "requiredIngredients": [
        {"name": "Rice", "requiredState": ["Boiled"]},
        {"name": "Cucumber", "requiredState": ["Cut"]},
        {"name": "Nori", "requiredState": ["Cut"]}
      ]
    },
    {
      "name": "fish and cucumber sushi",
      "canDeliver": true,
      "requiredIngredients": [
        {"name": "Rice", "requiredState": ["Boiled"]},
        {"name": "Fish", "requiredState": ["Cut"]},
        {"name": "Cucumber", "requiredState": ["Cut"]},
        {"name": "Nori", "requiredState": ["Cut"]}
      ]
    }
  ]

}

